{
  "FormId": "bec41bef-6956-48bc-b59f-c99121003372",
  "FormBehaviour": {
    "Id": "bec41bef-6956-48bc-b59f-c99121003372",
    "Name": "frmImportUsers",
    "Starter": true,
    "Title": "Excel Import",
    "SaveAndCloseButtonEnabled": true,
    "SaveAndNewButtonEnabled": true,
    "NavigationButtonsEnabled": true
  },
  "InstanceId": "945a74d9-d630-4b57-8876-afd64dc2a6ab",
  "Title": "Excel Import",
  "FormTitle": "frmImportUsers",
  "ControlIds": [
    "btnImport",
    "btnUpdate",
    "Column",
    "Column1",
    "Column10",
    "Column16",
    "Column17",
    "Column8",
    "DownloadExcelTemplate",
    "Label",
    "Label2",
    "Label3",
    "Label5",
    "Message",
    "RadioButtonList",
    "Row",
    "Row1",
    "Row12",
    "Row6",
    "Row8",
    "UploadFilewithData",
    "ValidateMessage"
  ],
  "Rows": [
    {
      "IsBorder": false,
      "ColumnsList": [
        {
          "Width": 12,
          "IsBorder": false,
          "IsDefaultColor": false,
          "BackColorEnable": false,
          "Controls": [
            {
              "$type": "Label",
              "Align": 3,
              "Font": "Segoe UI, 14pt",
              "BackColor": "0, 236, 233, 217",
              "BackColorHTML": "#ECE9D9",
              "ForeColor": "0, 0, 0, 1",
              "ForeColorHTML": "#000001",
              "HasHeight": true,
              "DesignerFontCss": "font-family:Segoe UI;font-size:14pt;",
              "LabelCss": "font-family:Segoe UI;font-size:14pt; color: var(--mud-palette-text-primary);",
              "ServerId": "Label",
              "Id": "Label",
              "ControlType": 2,
              "IsContainer": false,
              "ControlTypeName": "Label",
              "ParentColumnWidth": 12,
              "Behavior": {
                "Id": "00000000-0000-0000-0000-000000000000",
                "FormBehaviorId": "00000000-0000-0000-0000-000000000000",
                "ControlState": 0,
                "ControlStateEnum": 0,
                "IMSState": "editable",
                "Enabled": true,
                "Visible": true,
                "FormControlId": "00000000-0000-0000-0000-000000000000",
                "lastNonInvisibleState": 0
              },
              "Validators": [],
              "IsMandatory": false,
              "Caption": "Use  this form to import a user list directly into either EPC or DBP. \r\nIf users will have access to both, we recommend that you import the user list directly into EPC and then use the Synchronization with EPC application to import the list into DBP.",
              "CaptionPosition": 0,
              "CaptionFontSize": 0,
              "CaptionIsBold": false,
              "CaptionIsItalic": false,
              "CaptionIsUnderline": false,
              "CaptionBackColorT": "Transparent",
              "CaptionForeColorT": "#222222",
              "LabelStyle": "color: var(--mud-palette-text-primary) !important;background-color: Transparent;",
              "Tooltip": "The expected file is an Excel document (.xlsx) with the user list on Sheet1.\r\n\r\nThe column headers expected on the first row are:\r\n\r\nUserName, FirstName, MiddleName, LastName, Email, PhoneNumber, Password, Roles(s), Department, Epcadmin, Modeler, Portal, Active, Code, AltCode, Cell, Address, Description",
              "ParentId": "autoColumn2",
              "Order": 1,
              "CssCaptionFontSize": "16px",
              "CssCaptionFontWeight": "normal",
              "CssCaptionFontStyle": "normal",
              "CssCaptionTextDecoration": "normal",
              "CssCaptionColor": "var(--mud-palette-text-primary)",
              "CssCaptionBackgroundColor": "white"
            }
          ],
          "ServerId": "autoColumn2",
          "Id": "autoColumn2",
          "ControlType": 1,
          "IsContainer": true,
          "ControlTypeName": "Column",
          "ParentColumnWidth": 0,
          "Behavior": {
            "Id": "00000000-0000-0000-0000-000000000000",
            "FormBehaviorId": "00000000-0000-0000-0000-000000000000",
            "ControlState": 0,
            "ControlStateEnum": 0,
            "IMSState": "editable",
            "Enabled": true,
            "Visible": true,
            "FormControlId": "00000000-0000-0000-0000-000000000000",
            "lastNonInvisibleState": 0
          },
          "Validators": [],
          "IsMandatory": false,
          "CaptionPosition": 0,
          "CaptionFontSize": 0,
          "CaptionIsBold": false,
          "CaptionIsItalic": false,
          "CaptionIsUnderline": false,
          "CaptionBackColorT": "Transparent",
          "CaptionForeColorT": "#222222",
          "LabelStyle": "color: var(--mud-palette-text-primary) !important;background-color: Transparent;",
          "ParentId": "autoRow1",
          "Order": 0,
          "CssCaptionFontSize": "16px",
          "CssCaptionFontWeight": "normal",
          "CssCaptionFontStyle": "normal",
          "CssCaptionTextDecoration": "normal",
          "CssCaptionColor": "var(--mud-palette-text-primary)",
          "CssCaptionBackgroundColor": "white"
        }
      ],
      "Columns": [],
      "IsSection": false,
      "ServerId": "autoRow1",
      "Id": "autoRow1",
      "ControlType": 0,
      "IsContainer": true,
      "ControlTypeName": "Row",
      "ParentColumnWidth": 0,
      "Behavior": {
        "Id": "00000000-0000-0000-0000-000000000000",
        "FormBehaviorId": "00000000-0000-0000-0000-000000000000",
        "ControlState": 0,
        "ControlStateEnum": 0,
        "IMSState": "editable",
        "Enabled": true,
        "Visible": true,
        "FormControlId": "00000000-0000-0000-0000-000000000000",
        "lastNonInvisibleState": 0
      },
      "Validators": [],
      "IsMandatory": false,
      "CaptionPosition": 0,
      "CaptionFontSize": 0,
      "CaptionIsBold": false,
      "CaptionIsItalic": false,
      "CaptionIsUnderline": false,
      "CaptionBackColorT": "Transparent",
      "CaptionForeColorT": "#222222",
      "LabelStyle": "color: var(--mud-palette-text-primary) !important;background-color: Transparent;",
      "Order": 1,
      "CssCaptionFontSize": "16px",
      "CssCaptionFontWeight": "normal",
      "CssCaptionFontStyle": "normal",
      "CssCaptionTextDecoration": "normal",
      "CssCaptionColor": "var(--mud-palette-text-primary)",
      "CssCaptionBackgroundColor": "white"
    },
    {
      "IsBorder": false,
      "ColumnsList": [
        {
          "Width": 12,
          "IsBorder": false,
          "IsDefaultColor": false,
          "BackColorEnable": false,
          "Controls": [
            {
              "$type": "Label",
              "Align": 3,
              "Font": "Segoe UI, 14pt",
              "BackColor": "0, 236, 233, 217",
              "BackColorHTML": "#ECE9D9",
              "ForeColor": "0, 0, 0, 1",
              "ForeColorHTML": "#000001",
              "HasHeight": true,
              "DesignerFontCss": "font-family:Segoe UI;font-size:14pt;",
              "LabelCss": "font-family:Segoe UI;font-size:14pt; color: var(--mud-palette-text-primary);",
              "ServerId": "Label2",
              "Id": "Label2",
              "ControlType": 2,
              "IsContainer": false,
              "ControlTypeName": "Label",
              "ParentColumnWidth": 12,
              "Behavior": {
                "Id": "00000000-0000-0000-0000-000000000000",
                "FormBehaviorId": "00000000-0000-0000-0000-000000000000",
                "ControlState": 0,
                "ControlStateEnum": 0,
                "IMSState": "editable",
                "Enabled": true,
                "Visible": true,
                "FormControlId": "00000000-0000-0000-0000-000000000000",
                "lastNonInvisibleState": 0
              },
              "Validators": [],
              "IsMandatory": false,
              "Caption": "An exported user list from the Organization Management application can be used as a template.",
              "CaptionPosition": 0,
              "CaptionFontSize": 0,
              "CaptionIsBold": false,
              "CaptionIsItalic": false,
              "CaptionIsUnderline": false,
              "CaptionBackColorT": "Transparent",
              "CaptionForeColorT": "#222222",
              "LabelStyle": "color: var(--mud-palette-text-primary) !important;background-color: Transparent;",
              "Tooltip": "The column headers on the first row are:\r\n\r\nName, ID, Active, UserCode, Email, Tel, Address, Login, AlternativeCode, FirstName, LastName.",
              "ParentId": "autoColumn4",
              "Order": 2,
              "CssCaptionFontSize": "16px",
              "CssCaptionFontWeight": "normal",
              "CssCaptionFontStyle": "normal",
              "CssCaptionTextDecoration": "normal",
              "CssCaptionColor": "var(--mud-palette-text-primary)",
              "CssCaptionBackgroundColor": "white"
            }
          ],
          "ServerId": "autoColumn4",
          "Id": "autoColumn4",
          "ControlType": 1,
          "IsContainer": true,
          "ControlTypeName": "Column",
          "ParentColumnWidth": 0,
          "Behavior": {
            "Id": "00000000-0000-0000-0000-000000000000",
            "FormBehaviorId": "00000000-0000-0000-0000-000000000000",
            "ControlState": 0,
            "ControlStateEnum": 0,
            "IMSState": "editable",
            "Enabled": true,
            "Visible": true,
            "FormControlId": "00000000-0000-0000-0000-000000000000",
            "lastNonInvisibleState": 0
          },
          "Validators": [],
          "IsMandatory": false,
          "CaptionPosition": 0,
          "CaptionFontSize": 0,
          "CaptionIsBold": false,
          "CaptionIsItalic": false,
          "CaptionIsUnderline": false,
          "CaptionBackColorT": "Transparent",
          "CaptionForeColorT": "#222222",
          "LabelStyle": "color: var(--mud-palette-text-primary) !important;background-color: Transparent;",
          "ParentId": "autoRow3",
          "Order": 0,
          "CssCaptionFontSize": "16px",
          "CssCaptionFontWeight": "normal",
          "CssCaptionFontStyle": "normal",
          "CssCaptionTextDecoration": "normal",
          "CssCaptionColor": "var(--mud-palette-text-primary)",
          "CssCaptionBackgroundColor": "white"
        }
      ],
      "Columns": [],
      "IsSection": false,
      "ServerId": "autoRow3",
      "Id": "autoRow3",
      "ControlType": 0,
      "IsContainer": true,
      "ControlTypeName": "Row",
      "ParentColumnWidth": 0,
      "Behavior": {
        "Id": "00000000-0000-0000-0000-000000000000",
        "FormBehaviorId": "00000000-0000-0000-0000-000000000000",
        "ControlState": 0,
        "ControlStateEnum": 0,
        "IMSState": "editable",
        "Enabled": true,
        "Visible": true,
        "FormControlId": "00000000-0000-0000-0000-000000000000",
        "lastNonInvisibleState": 0
      },
      "Validators": [],
      "IsMandatory": false,
      "CaptionPosition": 0,
      "CaptionFontSize": 0,
      "CaptionIsBold": false,
      "CaptionIsItalic": false,
      "CaptionIsUnderline": false,
      "CaptionBackColorT": "Transparent",
      "CaptionForeColorT": "#222222",
      "LabelStyle": "color: var(--mud-palette-text-primary) !important;background-color: Transparent;",
      "Order": 2,
      "CssCaptionFontSize": "16px",
      "CssCaptionFontWeight": "normal",
      "CssCaptionFontStyle": "normal",
      "CssCaptionTextDecoration": "normal",
      "CssCaptionColor": "var(--mud-palette-text-primary)",
      "CssCaptionBackgroundColor": "white"
    },
    {
      "IsBorder": false,
      "ColumnsList": [
        {
          "Width": 12,
          "IsBorder": false,
          "IsDefaultColor": false,
          "BackColorEnable": false,
          "Controls": [
            {
              "$type": "Label",
              "Align": 3,
              "Font": "Segoe UI, 14pt",
              "BackColor": "0, 236, 233, 217",
              "BackColorHTML": "#ECE9D9",
              "ForeColor": "Black",
              "ForeColorHTML": "#Black",
              "HasHeight": true,
              "DesignerFontCss": "font-family:Segoe UI;font-size:14pt;;color:#000000;",
              "LabelCss": "font-family:Segoe UI;font-size:14pt;;color:#000000; color: #Black;",
              "ServerId": "Label3",
              "Id": "Label3",
              "ControlType": 2,
              "IsContainer": false,
              "ControlTypeName": "Label",
              "ParentColumnWidth": 12,
              "Behavior": {
                "Id": "00000000-0000-0000-0000-000000000000",
                "FormBehaviorId": "00000000-0000-0000-0000-000000000000",
                "ControlState": 0,
                "ControlStateEnum": 0,
                "IMSState": "editable",
                "Enabled": true,
                "Visible": true,
                "FormControlId": "00000000-0000-0000-0000-000000000000",
                "lastNonInvisibleState": 0
              },
              "Validators": [],
              "IsMandatory": false,
              "Caption": "For a new role, you will need to input the corresponding department. For an existing role, the department is not required.\r\nThe system will disregard a blank or null value under the \u0022Login\u0022 and/or \u0022Username\u0022 columns.\r\n\u2022 If you want to enable EPCAdmin, Modeler, and/or Portal for the user, input \u201CYes\u201D in the relevant fields. If you do not want to enable these permissions, instead leave the columns blank.\r\n\u2022 In the \u0022Active\u0022 column, input \u0022Yes\u0022 to mark the item as active. To mark it as inactive, leave the corresponding row blank.\r\n\u2022 In the Org. Management Excel file, the \u0022Active\u0022 column will instead contain \u0022True\u0022 or \u0022False\u0022 as values. These values will still be accepted by the system.\r\n",
              "CaptionPosition": 0,
              "CaptionFontSize": 0,
              "CaptionIsBold": false,
              "CaptionIsItalic": false,
              "CaptionIsUnderline": false,
              "CaptionBackColorT": "Transparent",
              "CaptionForeColorT": "#222222",
              "LabelStyle": "color: var(--mud-palette-text-primary) !important;background-color: Transparent;",
              "ParentId": "autoColumn6",
              "Order": 3,
              "CssCaptionFontSize": "16px",
              "CssCaptionFontWeight": "normal",
              "CssCaptionFontStyle": "normal",
              "CssCaptionTextDecoration": "normal",
              "CssCaptionColor": "var(--mud-palette-text-primary)",
              "CssCaptionBackgroundColor": "white"
            }
          ],
          "ServerId": "autoColumn6",
          "Id": "autoColumn6",
          "ControlType": 1,
          "IsContainer": true,
          "ControlTypeName": "Column",
          "ParentColumnWidth": 0,
          "Behavior": {
            "Id": "00000000-0000-0000-0000-000000000000",
            "FormBehaviorId": "00000000-0000-0000-0000-000000000000",
            "ControlState": 0,
            "ControlStateEnum": 0,
            "IMSState": "editable",
            "Enabled": true,
            "Visible": true,
            "FormControlId": "00000000-0000-0000-0000-000000000000",
            "lastNonInvisibleState": 0
          },
          "Validators": [],
          "IsMandatory": false,
          "CaptionPosition": 0,
          "CaptionFontSize": 0,
          "CaptionIsBold": false,
          "CaptionIsItalic": false,
          "CaptionIsUnderline": false,
          "CaptionBackColorT": "Transparent",
          "CaptionForeColorT": "#222222",
          "LabelStyle": "color: var(--mud-palette-text-primary) !important;background-color: Transparent;",
          "ParentId": "autoRow5",
          "Order": 0,
          "CssCaptionFontSize": "16px",
          "CssCaptionFontWeight": "normal",
          "CssCaptionFontStyle": "normal",
          "CssCaptionTextDecoration": "normal",
          "CssCaptionColor": "var(--mud-palette-text-primary)",
          "CssCaptionBackgroundColor": "white"
        }
      ],
      "Columns": [],
      "IsSection": false,
      "ServerId": "autoRow5",
      "Id": "autoRow5",
      "ControlType": 0,
      "IsContainer": true,
      "ControlTypeName": "Row",
      "ParentColumnWidth": 0,
      "Behavior": {
        "Id": "00000000-0000-0000-0000-000000000000",
        "FormBehaviorId": "00000000-0000-0000-0000-000000000000",
        "ControlState": 0,
        "ControlStateEnum": 0,
        "IMSState": "editable",
        "Enabled": true,
        "Visible": true,
        "FormControlId": "00000000-0000-0000-0000-000000000000",
        "lastNonInvisibleState": 0
      },
      "Validators": [],
      "IsMandatory": false,
      "CaptionPosition": 0,
      "CaptionFontSize": 0,
      "CaptionIsBold": false,
      "CaptionIsItalic": false,
      "CaptionIsUnderline": false,
      "CaptionBackColorT": "Transparent",
      "CaptionForeColorT": "#222222",
      "LabelStyle": "color: var(--mud-palette-text-primary) !important;background-color: Transparent;",
      "Order": 3,
      "CssCaptionFontSize": "16px",
      "CssCaptionFontWeight": "normal",
      "CssCaptionFontStyle": "normal",
      "CssCaptionTextDecoration": "normal",
      "CssCaptionColor": "var(--mud-palette-text-primary)",
      "CssCaptionBackgroundColor": "white"
    },
    {
      "IsBorder": false,
      "ColumnsList": [
        {
          "Width": 12,
          "IsBorder": false,
          "IsDefaultColor": false,
          "BackColorEnable": false,
          "Controls": [
            {
              "$type": "Label",
              "Align": 3,
              "Font": "Segoe UI, 14pt",
              "BackColor": "0, 236, 233, 217",
              "BackColorHTML": "#ECE9D9",
              "ForeColor": "240, 0, 0",
              "ForeColorHTML": "#F00000",
              "HasHeight": true,
              "DesignerFontCss": "font-family:Segoe UI;font-size:14pt;;color:#F00000;",
              "LabelCss": "font-family:Segoe UI;font-size:14pt;;color:#F00000; color: #F00000;",
              "ServerId": "Label5",
              "Id": "Label5",
              "ControlType": 2,
              "IsContainer": false,
              "ControlTypeName": "Label",
              "ParentColumnWidth": 12,
              "Behavior": {
                "Id": "00000000-0000-0000-0000-000000000000",
                "FormBehaviorId": "00000000-0000-0000-0000-000000000000",
                "ControlState": 0,
                "ControlStateEnum": 0,
                "IMSState": "editable",
                "Enabled": true,
                "Visible": true,
                "FormControlId": "00000000-0000-0000-0000-000000000000",
                "lastNonInvisibleState": 0
              },
              "Validators": [],
              "IsMandatory": false,
              "Caption": "If the list is imported directly into EPC, only the users will be added to the system. You will need to manually link/create the corresponding roles and departments for each user.",
              "CaptionPosition": 0,
              "CaptionFontSize": 0,
              "CaptionIsBold": false,
              "CaptionIsItalic": false,
              "CaptionIsUnderline": false,
              "CaptionBackColorT": "Transparent",
              "CaptionForeColorT": "#222222",
              "LabelStyle": "color: var(--mud-palette-text-primary) !important;background-color: Transparent;",
              "ParentId": "autoColumn8",
              "Order": 4,
              "CssCaptionFontSize": "16px",
              "CssCaptionFontWeight": "normal",
              "CssCaptionFontStyle": "normal",
              "CssCaptionTextDecoration": "normal",
              "CssCaptionColor": "var(--mud-palette-text-primary)",
              "CssCaptionBackgroundColor": "white"
            }
          ],
          "ServerId": "autoColumn8",
          "Id": "autoColumn8",
          "ControlType": 1,
          "IsContainer": true,
          "ControlTypeName": "Column",
          "ParentColumnWidth": 0,
          "Behavior": {
            "Id": "00000000-0000-0000-0000-000000000000",
            "FormBehaviorId": "00000000-0000-0000-0000-000000000000",
            "ControlState": 0,
            "ControlStateEnum": 0,
            "IMSState": "editable",
            "Enabled": true,
            "Visible": true,
            "FormControlId": "00000000-0000-0000-0000-000000000000",
            "lastNonInvisibleState": 0
          },
          "Validators": [],
          "IsMandatory": false,
          "CaptionPosition": 0,
          "CaptionFontSize": 0,
          "CaptionIsBold": false,
          "CaptionIsItalic": false,
          "CaptionIsUnderline": false,
          "CaptionBackColorT": "Transparent",
          "CaptionForeColorT": "#222222",
          "LabelStyle": "color: var(--mud-palette-text-primary) !important;background-color: Transparent;",
          "ParentId": "autoRow7",
          "Order": 0,
          "CssCaptionFontSize": "16px",
          "CssCaptionFontWeight": "normal",
          "CssCaptionFontStyle": "normal",
          "CssCaptionTextDecoration": "normal",
          "CssCaptionColor": "var(--mud-palette-text-primary)",
          "CssCaptionBackgroundColor": "white"
        }
      ],
      "Columns": [],
      "IsSection": false,
      "ServerId": "autoRow7",
      "Id": "autoRow7",
      "ControlType": 0,
      "IsContainer": true,
      "ControlTypeName": "Row",
      "ParentColumnWidth": 0,
      "Behavior": {
        "Id": "00000000-0000-0000-0000-000000000000",
        "FormBehaviorId": "00000000-0000-0000-0000-000000000000",
        "ControlState": 0,
        "ControlStateEnum": 0,
        "IMSState": "editable",
        "Enabled": true,
        "Visible": true,
        "FormControlId": "00000000-0000-0000-0000-000000000000",
        "lastNonInvisibleState": 0
      },
      "Validators": [],
      "IsMandatory": false,
      "CaptionPosition": 0,
      "CaptionFontSize": 0,
      "CaptionIsBold": false,
      "CaptionIsItalic": false,
      "CaptionIsUnderline": false,
      "CaptionBackColorT": "Transparent",
      "CaptionForeColorT": "#222222",
      "LabelStyle": "color: var(--mud-palette-text-primary) !important;background-color: Transparent;",
      "Order": 4,
      "CssCaptionFontSize": "16px",
      "CssCaptionFontWeight": "normal",
      "CssCaptionFontStyle": "normal",
      "CssCaptionTextDecoration": "normal",
      "CssCaptionColor": "var(--mud-palette-text-primary)",
      "CssCaptionBackgroundColor": "white"
    },
    {
      "IsBorder": false,
      "ColumnsList": [
        {
          "Width": 12,
          "IsBorder": false,
          "IsDefaultColor": false,
          "BackColorEnable": false,
          "Controls": [
            {
              "$type": "Label",
              "Align": 3,
              "Font": "Tahoma, 9pt",
              "BackColor": "0, 236, 233, 217",
              "BackColorHTML": "#ECE9D9",
              "ForeColor": "0, 0, 0, 1",
              "ForeColorHTML": "#000001",
              "HasHeight": false,
              "DesignerFontCss": "font-family:Tahoma;font-size:9pt;",
              "LabelCss": "font-family:Tahoma;font-size:9pt; color: var(--mud-palette-text-primary);",
              "ServerId": "ValidateMessage",
              "Id": "ValidateMessage",
              "ControlType": 2,
              "IsContainer": false,
              "ControlTypeName": "Label",
              "ParentColumnWidth": 12,
              "Binding": {
                "Id": "03097066-6d65-4ac3-88ae-aec3009542c5",
                "PhysicalFormId": "14a0ca1c-e783-4003-b109-aec200916cca",
                "FormObjectField": "ValidationMessage",
                "FormObjectFieldType": "System.String",
                "AutoPostBack": false,
                "IsNotPostBack": false,
                "FormControlId": "9ca58471-c6e4-42d3-ab6f-aec300951a8b"
              },
              "Behavior": {
                "Id": "00000000-0000-0000-0000-000000000000",
                "FormBehaviorId": "00000000-0000-0000-0000-000000000000",
                "ControlState": 0,
                "ControlStateEnum": 0,
                "IMSState": "editable",
                "Enabled": true,
                "Visible": true,
                "FormControlId": "00000000-0000-0000-0000-000000000000",
                "lastNonInvisibleState": 0
              },
              "Validators": [],
              "IsMandatory": false,
              "Caption": "",
              "CaptionPosition": 0,
              "CaptionFontSize": 0,
              "CaptionIsBold": false,
              "CaptionIsItalic": false,
              "CaptionIsUnderline": false,
              "CaptionBackColorT": "Transparent",
              "CaptionForeColorT": "#222222",
              "LabelStyle": "color: var(--mud-palette-text-primary) !important;background-color: Transparent;",
              "ParentId": "autoColumn10",
              "Order": 5,
              "CssCaptionFontSize": "16px",
              "CssCaptionFontWeight": "normal",
              "CssCaptionFontStyle": "normal",
              "CssCaptionTextDecoration": "normal",
              "CssCaptionColor": "var(--mud-palette-text-primary)",
              "CssCaptionBackgroundColor": "white"
            }
          ],
          "ServerId": "autoColumn10",
          "Id": "autoColumn10",
          "ControlType": 1,
          "IsContainer": true,
          "ControlTypeName": "Column",
          "ParentColumnWidth": 0,
          "Behavior": {
            "Id": "00000000-0000-0000-0000-000000000000",
            "FormBehaviorId": "00000000-0000-0000-0000-000000000000",
            "ControlState": 0,
            "ControlStateEnum": 0,
            "IMSState": "editable",
            "Enabled": true,
            "Visible": true,
            "FormControlId": "00000000-0000-0000-0000-000000000000",
            "lastNonInvisibleState": 0
          },
          "Validators": [],
          "IsMandatory": false,
          "CaptionPosition": 0,
          "CaptionFontSize": 0,
          "CaptionIsBold": false,
          "CaptionIsItalic": false,
          "CaptionIsUnderline": false,
          "CaptionBackColorT": "Transparent",
          "CaptionForeColorT": "#222222",
          "LabelStyle": "color: var(--mud-palette-text-primary) !important;background-color: Transparent;",
          "ParentId": "autoRow9",
          "Order": 0,
          "CssCaptionFontSize": "16px",
          "CssCaptionFontWeight": "normal",
          "CssCaptionFontStyle": "normal",
          "CssCaptionTextDecoration": "normal",
          "CssCaptionColor": "var(--mud-palette-text-primary)",
          "CssCaptionBackgroundColor": "white"
        }
      ],
      "Columns": [],
      "IsSection": false,
      "ServerId": "autoRow9",
      "Id": "autoRow9",
      "ControlType": 0,
      "IsContainer": true,
      "ControlTypeName": "Row",
      "ParentColumnWidth": 0,
      "Behavior": {
        "Id": "00000000-0000-0000-0000-000000000000",
        "FormBehaviorId": "00000000-0000-0000-0000-000000000000",
        "ControlState": 0,
        "ControlStateEnum": 0,
        "IMSState": "editable",
        "Enabled": true,
        "Visible": true,
        "FormControlId": "00000000-0000-0000-0000-000000000000",
        "lastNonInvisibleState": 0
      },
      "Validators": [],
      "IsMandatory": false,
      "CaptionPosition": 0,
      "CaptionFontSize": 0,
      "CaptionIsBold": false,
      "CaptionIsItalic": false,
      "CaptionIsUnderline": false,
      "CaptionBackColorT": "Transparent",
      "CaptionForeColorT": "#222222",
      "LabelStyle": "color: var(--mud-palette-text-primary) !important;background-color: Transparent;",
      "Order": 5,
      "CssCaptionFontSize": "16px",
      "CssCaptionFontWeight": "normal",
      "CssCaptionFontStyle": "normal",
      "CssCaptionTextDecoration": "normal",
      "CssCaptionColor": "var(--mud-palette-text-primary)",
      "CssCaptionBackgroundColor": "white"
    },
    {
      "IsBorder": false,
      "BorderColor": "Black",
      "ColorRgba": "#000000",
      "ColumnsList": [
        {
          "Width": 6,
          "IsBorder": false,
          "IsDefaultColor": false,
          "BackColorEnable": true,
          "BorderColor": "Black",
          "ColorRgba": "#000000",
          "BackgroundColor": "Transparent",
          "BackgroundColorRgba": "#ffffff",
          "Controls": [
            {
              "$type": "FileAttachment",
              "MaxFileSize": 2,
              "MaxFileCount": 2,
              "FileTypes": [],
              "ServerId": "DownloadExcelTemplate",
              "Id": "DownloadExcelTemplate",
              "ControlType": 11,
              "IsContainer": false,
              "ControlTypeName": "FileAttachment",
              "ParentColumnWidth": 6,
              "Binding": {
                "Id": "17f92e8e-6faa-4386-800c-aec800cdd937",
                "PhysicalFormId": "14a0ca1c-e783-4003-b109-aec200916cca",
                "FormObjectField": "ImportFileTemplate",
                "FormObjectFieldType": "System.String",
                "AutoPostBack": false,
                "IsNotPostBack": false,
                "FormControlId": "b6bf09a5-514c-4985-a560-aec800cd32a5"
              },
              "Behavior": {
                "Id": "382d0e8d-4b87-48b8-90c0-b2aa011c5677",
                "FormBehaviorId": "bec41bef-6956-48bc-b59f-c99121003372",
                "ControlState": 0,
                "ControlStateEnum": 0,
                "IMSState": "editable",
                "Enabled": true,
                "Visible": true,
                "EnableNestedEdit": false,
                "EnableNestedNew": false,
                "EnableNestedDelete": false,
                "EnableNestedView": false,
                "EnableAttachmentUpload": false,
                "EnableAttachmentDelete": false,
                "EnableAttachmentDownload": true,
                "PreAttachedFiles": "9b030e18-0c38-4ae5-8ce0-ae79aca1d66b",
                "EnableNestedSelect": false,
                "EnableInlineNew": false,
                "EnableInlineEdit": false,
                "FormControlId": "b6bf09a5-514c-4985-a560-aec800cd32a5",
                "EnableGanttNew": false,
                "EnableGanttDelete": false,
                "EnableAttachmentScan": true,
                "EnableAttachmentEdit": false,
                "EnableAttachmentRevert": false,
                "EnableAttachmentNewVersion": false,
                "RemoveType": 0,
                "lastNonInvisibleState": 0
              },
              "Validators": [],
              "IsMandatory": false,
              "Caption": "Download Excel Template",
              "CaptionPosition": 0,
              "CaptionFontSize": 16,
              "CaptionIsBold": true,
              "CaptionIsItalic": false,
              "CaptionIsUnderline": false,
              "CaptionBackColorT": "Transparent",
              "CaptionForeColorT": "#222222",
              "LabelStyle": "font-size: 16px;font-weight: bold;color: var(--mud-palette-text-primary) !important;background-color: Transparent;",
              "Tooltip": "Click on the file to download",
              "ParentId": "Column16",
              "Order": 0,
              "CssCaptionFontSize": "16px",
              "CssCaptionFontWeight": "normal",
              "CssCaptionFontStyle": "normal",
              "CssCaptionTextDecoration": "normal",
              "CssCaptionColor": "var(--mud-palette-text-primary)",
              "CssCaptionBackgroundColor": "white"
            }
          ],
          "ServerId": "Column16",
          "Id": "Column16",
          "ControlType": 1,
          "IsContainer": true,
          "ControlTypeName": "Column",
          "ParentColumnWidth": 0,
          "Behavior": {
            "Id": "50d2cba4-c641-4bd2-9017-b2aa011c567c",
            "FormBehaviorId": "bec41bef-6956-48bc-b59f-c99121003372",
            "ControlState": 0,
            "ControlStateEnum": 0,
            "IMSState": "editable",
            "Enabled": true,
            "Visible": true,
            "EnableNestedEdit": false,
            "EnableNestedNew": false,
            "EnableNestedDelete": false,
            "EnableNestedView": false,
            "EnableAttachmentUpload": true,
            "EnableAttachmentDelete": true,
            "EnableAttachmentDownload": true,
            "EnableNestedSelect": false,
            "EnableInlineNew": false,
            "EnableInlineEdit": false,
            "FormControlId": "941aae7c-09ae-4790-81ed-af10007f7295",
            "EnableGanttNew": false,
            "EnableGanttDelete": false,
            "EnableAttachmentScan": true,
            "EnableAttachmentEdit": false,
            "EnableAttachmentRevert": false,
            "EnableAttachmentNewVersion": false,
            "RemoveType": 0,
            "lastNonInvisibleState": 0
          },
          "Validators": [],
          "IsMandatory": false,
          "Caption": "Column",
          "CaptionPosition": 0,
          "CaptionFontSize": 0,
          "CaptionIsBold": false,
          "CaptionIsItalic": false,
          "CaptionIsUnderline": false,
          "CaptionBackColorT": "Transparent",
          "CaptionForeColorT": "#222222",
          "LabelStyle": "color: var(--mud-palette-text-primary) !important;background-color: Transparent;",
          "ParentId": "Row12",
          "Order": 0,
          "CssCaptionFontSize": "16px",
          "CssCaptionFontWeight": "normal",
          "CssCaptionFontStyle": "normal",
          "CssCaptionTextDecoration": "normal",
          "CssCaptionColor": "var(--mud-palette-text-primary)",
          "CssCaptionBackgroundColor": "white"
        },
        {
          "Width": 6,
          "IsBorder": false,
          "IsDefaultColor": false,
          "BackColorEnable": true,
          "BorderColor": "Black",
          "ColorRgba": "#000000",
          "BackgroundColor": "Transparent",
          "BackgroundColorRgba": "#ffffff",
          "Controls": [
            {
              "$type": "FileAttachment",
              "MaxFileSize": 2,
              "MaxFileCount": 2,
              "FileTypes": [],
              "ServerId": "UploadFilewithData",
              "Id": "UploadFilewithData",
              "ControlType": 11,
              "IsContainer": false,
              "ControlTypeName": "FileAttachment",
              "ParentColumnWidth": 6,
              "Binding": {
                "Id": "732a8e6f-ff58-4c3d-89e9-aec20099f71a",
                "PhysicalFormId": "14a0ca1c-e783-4003-b109-aec200916cca",
                "FormObjectField": "ImportFile",
                "FormObjectFieldType": "System.String",
                "AutoPostBack": false,
                "IsNotPostBack": false,
                "FormControlId": "a02a7abc-10e0-4267-bc58-aec2009984d9"
              },
              "Behavior": {
                "Id": "bbb3f8f0-23d4-4f5a-9b18-b2aa011c567c",
                "FormBehaviorId": "bec41bef-6956-48bc-b59f-c99121003372",
                "ControlState": 0,
                "ControlStateEnum": 0,
                "IMSState": "editable",
                "Enabled": true,
                "Visible": true,
                "EnableNestedEdit": false,
                "EnableNestedNew": false,
                "EnableNestedDelete": false,
                "EnableNestedView": false,
                "EnableAttachmentUpload": true,
                "EnableAttachmentDelete": true,
                "EnableAttachmentDownload": true,
                "EnableNestedSelect": false,
                "EnableInlineNew": false,
                "EnableInlineEdit": false,
                "FormControlId": "a02a7abc-10e0-4267-bc58-aec2009984d9",
                "EnableGanttNew": false,
                "EnableGanttDelete": false,
                "EnableAttachmentScan": true,
                "EnableAttachmentEdit": false,
                "EnableAttachmentRevert": false,
                "EnableAttachmentNewVersion": false,
                "RemoveType": 0,
                "lastNonInvisibleState": 0
              },
              "Validators": [
                {
                  "ControlToValidate": "UploadFilewithData",
                  "ControlType": 11,
                  "Error": "Please enter a value for \u0022Upload File with Data\u0022",
                  "Visible": true,
                  "ValidationType": 0
                }
              ],
              "IsMandatory": true,
              "Caption": "Upload File with Data",
              "CaptionPosition": 0,
              "CaptionFontSize": 16,
              "CaptionIsBold": true,
              "CaptionIsItalic": false,
              "CaptionIsUnderline": false,
              "CaptionBackColorT": "Transparent",
              "CaptionForeColorT": "#222222",
              "LabelStyle": "font-size: 16px;font-weight: bold;color: var(--mud-palette-text-primary) !important;background-color: Transparent;",
              "ParentId": "Column17",
              "Order": 0,
              "CssCaptionFontSize": "16px",
              "CssCaptionFontWeight": "normal",
              "CssCaptionFontStyle": "normal",
              "CssCaptionTextDecoration": "normal",
              "CssCaptionColor": "var(--mud-palette-text-primary)",
              "CssCaptionBackgroundColor": "white"
            }
          ],
          "ServerId": "Column17",
          "Id": "Column17",
          "ControlType": 1,
          "IsContainer": true,
          "ControlTypeName": "Column",
          "ParentColumnWidth": 0,
          "Behavior": {
            "Id": "bf0ca110-68e0-4c30-9745-b2aa011c567c",
            "FormBehaviorId": "bec41bef-6956-48bc-b59f-c99121003372",
            "ControlState": 0,
            "ControlStateEnum": 0,
            "IMSState": "editable",
            "Enabled": true,
            "Visible": true,
            "EnableNestedEdit": false,
            "EnableNestedNew": false,
            "EnableNestedDelete": false,
            "EnableNestedView": false,
            "EnableAttachmentUpload": true,
            "EnableAttachmentDelete": true,
            "EnableAttachmentDownload": true,
            "EnableNestedSelect": false,
            "EnableInlineNew": false,
            "EnableInlineEdit": false,
            "FormControlId": "fb8319de-c396-4ec7-97b0-af10007f73de",
            "EnableGanttNew": false,
            "EnableGanttDelete": false,
            "EnableAttachmentScan": true,
            "EnableAttachmentEdit": false,
            "EnableAttachmentRevert": false,
            "EnableAttachmentNewVersion": false,
            "RemoveType": 0,
            "lastNonInvisibleState": 0
          },
          "Validators": [],
          "IsMandatory": false,
          "Caption": "Column",
          "CaptionPosition": 0,
          "CaptionFontSize": 0,
          "CaptionIsBold": false,
          "CaptionIsItalic": false,
          "CaptionIsUnderline": false,
          "CaptionBackColorT": "Transparent",
          "CaptionForeColorT": "#222222",
          "LabelStyle": "color: var(--mud-palette-text-primary) !important;background-color: Transparent;",
          "ParentId": "Row12",
          "Order": 1,
          "CssCaptionFontSize": "16px",
          "CssCaptionFontWeight": "normal",
          "CssCaptionFontStyle": "normal",
          "CssCaptionTextDecoration": "normal",
          "CssCaptionColor": "var(--mud-palette-text-primary)",
          "CssCaptionBackgroundColor": "white"
        }
      ],
      "Columns": [
        4,
        4,
        4
      ],
      "IsSection": false,
      "ServerId": "Row12",
      "Id": "Row12",
      "ControlType": 0,
      "IsContainer": true,
      "ControlTypeName": "Row",
      "ParentColumnWidth": 0,
      "Behavior": {
        "Id": "108c431c-1c90-4b74-aa01-b2aa011c5673",
        "FormBehaviorId": "bec41bef-6956-48bc-b59f-c99121003372",
        "ControlState": 0,
        "ControlStateEnum": 0,
        "IMSState": "editable",
        "Enabled": true,
        "Visible": true,
        "EnableNestedEdit": false,
        "EnableNestedNew": false,
        "EnableNestedDelete": false,
        "EnableNestedView": false,
        "EnableAttachmentUpload": true,
        "EnableAttachmentDelete": true,
        "EnableAttachmentDownload": true,
        "EnableNestedSelect": false,
        "EnableInlineNew": false,
        "EnableInlineEdit": false,
        "FormControlId": "0479ba46-876a-4656-a16b-af10007f7152",
        "EnableGanttNew": false,
        "EnableGanttDelete": false,
        "EnableAttachmentScan": true,
        "EnableAttachmentEdit": false,
        "EnableAttachmentRevert": false,
        "EnableAttachmentNewVersion": false,
        "RemoveType": 0,
        "lastNonInvisibleState": 0
      },
      "Validators": [],
      "IsMandatory": false,
      "CaptionPosition": 0,
      "CaptionFontSize": 0,
      "CaptionIsBold": false,
      "CaptionIsItalic": false,
      "CaptionIsUnderline": false,
      "CaptionBackColorT": "Transparent",
      "CaptionForeColorT": "#222222",
      "LabelStyle": "color: var(--mud-palette-text-primary) !important;background-color: Transparent;",
      "Order": 6,
      "CssCaptionFontSize": "16px",
      "CssCaptionFontWeight": "normal",
      "CssCaptionFontStyle": "normal",
      "CssCaptionTextDecoration": "normal",
      "CssCaptionColor": "var(--mud-palette-text-primary)",
      "CssCaptionBackgroundColor": "white"
    },
    {
      "IsBorder": false,
      "ColumnsList": [
        {
          "Width": 12,
          "IsBorder": false,
          "IsDefaultColor": false,
          "BackColorEnable": false,
          "Controls": [
            {
              "$type": "RadioList",
              "Items": [
                {
                  "Enabled": true,
                  "Selected": false,
                  "Value": "0",
                  "Text": "DBP"
                },
                {
                  "Enabled": true,
                  "Selected": false,
                  "Value": "1",
                  "Text": "EPC"
                }
              ],
              "RepeatDirection": 1,
              "Columns": 1,
              "ServerId": "RadioButtonList",
              "Id": "RadioButtonList",
              "ControlType": 10,
              "IsContainer": false,
              "ControlTypeName": "RadioList",
              "ParentColumnWidth": 12,
              "Binding": {
                "Id": "8dc644d2-2799-4c35-9bdc-aec300904bf4",
                "PhysicalFormId": "14a0ca1c-e783-4003-b109-aec200916cca",
                "FormObjectField": "ExportType",
                "FormObjectFieldType": "System.Boolean",
                "AutoPostBack": false,
                "IsNotPostBack": false,
                "FormControlId": "32e443ae-e19b-4bee-a6c8-aec3008f8b58"
              },
              "Behavior": {
                "Id": "5b053fb3-37f1-45d2-ac26-b2aa011c567c",
                "FormBehaviorId": "bec41bef-6956-48bc-b59f-c99121003372",
                "ControlState": 0,
                "ControlStateEnum": 0,
                "IMSState": "editable",
                "Enabled": true,
                "Visible": true,
                "EnableNestedEdit": false,
                "EnableNestedNew": false,
                "EnableNestedDelete": false,
                "EnableNestedView": false,
                "EnableAttachmentUpload": true,
                "EnableAttachmentDelete": true,
                "EnableAttachmentDownload": true,
                "InitValue": "0",
                "EnableNestedSelect": false,
                "EnableInlineNew": false,
                "EnableInlineEdit": false,
                "FormControlId": "32e443ae-e19b-4bee-a6c8-aec3008f8b58",
                "EnableGanttNew": false,
                "EnableGanttDelete": false,
                "EnableAttachmentScan": true,
                "EnableAttachmentEdit": false,
                "EnableAttachmentRevert": false,
                "EnableAttachmentNewVersion": false,
                "RemoveType": 0,
                "lastNonInvisibleState": 0
              },
              "Validators": [],
              "IsMandatory": false,
              "Caption": "Export to",
              "CaptionPosition": 0,
              "CaptionFontSize": 16,
              "CaptionIsBold": true,
              "CaptionIsItalic": false,
              "CaptionIsUnderline": false,
              "CaptionBackColorT": "Transparent",
              "CaptionForeColorT": "#222222",
              "LabelStyle": "font-size: 16px;font-weight: bold;color: var(--mud-palette-text-primary) !important;background-color: Transparent;",
              "ParentId": "autoColumn12",
              "Order": 7,
              "CssCaptionFontSize": "16px",
              "CssCaptionFontWeight": "normal",
              "CssCaptionFontStyle": "normal",
              "CssCaptionTextDecoration": "normal",
              "CssCaptionColor": "var(--mud-palette-text-primary)",
              "CssCaptionBackgroundColor": "white"
            }
          ],
          "ServerId": "autoColumn12",
          "Id": "autoColumn12",
          "ControlType": 1,
          "IsContainer": true,
          "ControlTypeName": "Column",
          "ParentColumnWidth": 0,
          "Behavior": {
            "Id": "00000000-0000-0000-0000-000000000000",
            "FormBehaviorId": "00000000-0000-0000-0000-000000000000",
            "ControlState": 0,
            "ControlStateEnum": 0,
            "IMSState": "editable",
            "Enabled": true,
            "Visible": true,
            "FormControlId": "00000000-0000-0000-0000-000000000000",
            "lastNonInvisibleState": 0
          },
          "Validators": [],
          "IsMandatory": false,
          "CaptionPosition": 0,
          "CaptionFontSize": 0,
          "CaptionIsBold": false,
          "CaptionIsItalic": false,
          "CaptionIsUnderline": false,
          "CaptionBackColorT": "Transparent",
          "CaptionForeColorT": "#222222",
          "LabelStyle": "color: var(--mud-palette-text-primary) !important;background-color: Transparent;",
          "ParentId": "autoRow11",
          "Order": 0,
          "CssCaptionFontSize": "16px",
          "CssCaptionFontWeight": "normal",
          "CssCaptionFontStyle": "normal",
          "CssCaptionTextDecoration": "normal",
          "CssCaptionColor": "var(--mud-palette-text-primary)",
          "CssCaptionBackgroundColor": "white"
        }
      ],
      "Columns": [],
      "IsSection": false,
      "ServerId": "autoRow11",
      "Id": "autoRow11",
      "ControlType": 0,
      "IsContainer": true,
      "ControlTypeName": "Row",
      "ParentColumnWidth": 0,
      "Behavior": {
        "Id": "00000000-0000-0000-0000-000000000000",
        "FormBehaviorId": "00000000-0000-0000-0000-000000000000",
        "ControlState": 0,
        "ControlStateEnum": 0,
        "IMSState": "editable",
        "Enabled": true,
        "Visible": true,
        "FormControlId": "00000000-0000-0000-0000-000000000000",
        "lastNonInvisibleState": 0
      },
      "Validators": [],
      "IsMandatory": false,
      "CaptionPosition": 0,
      "CaptionFontSize": 0,
      "CaptionIsBold": false,
      "CaptionIsItalic": false,
      "CaptionIsUnderline": false,
      "CaptionBackColorT": "Transparent",
      "CaptionForeColorT": "#222222",
      "LabelStyle": "color: var(--mud-palette-text-primary) !important;background-color: Transparent;",
      "Order": 7,
      "CssCaptionFontSize": "16px",
      "CssCaptionFontWeight": "normal",
      "CssCaptionFontStyle": "normal",
      "CssCaptionTextDecoration": "normal",
      "CssCaptionColor": "var(--mud-palette-text-primary)",
      "CssCaptionBackgroundColor": "white"
    },
    {
      "IsBorder": false,
      "BorderColor": "Black",
      "ColorRgba": "#000000",
      "ColumnsList": [
        {
          "Width": 12,
          "IsBorder": false,
          "IsDefaultColor": false,
          "BackColorEnable": true,
          "BorderColor": "Black",
          "ColorRgba": "#000000",
          "BackgroundColor": "Transparent",
          "BackgroundColorRgba": "#ffffff",
          "Controls": [
            {
              "$type": "Row",
              "IsBorder": false,
              "BorderColor": "Black",
              "ColorRgba": "#000000",
              "ColumnsList": [
                {
                  "Width": 12,
                  "IsBorder": false,
                  "IsDefaultColor": false,
                  "BackColorEnable": true,
                  "BorderColor": "Black",
                  "ColorRgba": "#000000",
                  "BackgroundColor": "Transparent",
                  "BackgroundColorRgba": "#ffffff",
                  "Controls": [
                    {
                      "$type": "Button",
                      "Style": 1,
                      "Size": 0,
                      "IsBlock": false,
                      "DefaultAction": 0,
                      "ServerId": "btnImport",
                      "Id": "btnImport",
                      "ControlType": 13,
                      "IsContainer": false,
                      "ControlTypeName": "Button",
                      "ParentColumnWidth": 12,
                      "Binding": {
                        "Id": "403c9953-9a12-4dd6-a596-aec20099f71a",
                        "PhysicalFormId": "14a0ca1c-e783-4003-b109-aec200916cca",
                        "FormObjectField": "none",
                        "FormObjectFieldType": "none",
                        "CodeItemId": "87c7fbe7-8964-4efe-af79-aec200d1268a",
                        "AutoPostBack": true,
                        "IsNotPostBack": false,
                        "FormControlId": "12dc9591-c8ba-415a-9389-aec20099a4b7"
                      },
                      "Behavior": {
                        "Id": "b9419660-7c59-4c62-bdc8-b2aa011c5673",
                        "FormBehaviorId": "bec41bef-6956-48bc-b59f-c99121003372",
                        "ControlState": 0,
                        "ControlStateEnum": 0,
                        "IMSState": "editable",
                        "Enabled": true,
                        "Visible": true,
                        "EnableNestedEdit": false,
                        "EnableNestedNew": false,
                        "EnableNestedDelete": false,
                        "EnableNestedView": false,
                        "EnableAttachmentUpload": true,
                        "EnableAttachmentDelete": true,
                        "EnableAttachmentDownload": true,
                        "EnableNestedSelect": false,
                        "EnableInlineNew": false,
                        "EnableInlineEdit": false,
                        "FormControlId": "12dc9591-c8ba-415a-9389-aec20099a4b7",
                        "EnableGanttNew": false,
                        "EnableGanttDelete": false,
                        "EnableAttachmentScan": true,
                        "EnableAttachmentEdit": false,
                        "EnableAttachmentRevert": false,
                        "EnableAttachmentNewVersion": false,
                        "RemoveType": 0,
                        "lastNonInvisibleState": 0
                      },
                      "Validators": [],
                      "IsMandatory": false,
                      "Caption": "Import User List",
                      "CaptionPosition": 0,
                      "CaptionFontSize": 0,
                      "CaptionIsBold": false,
                      "CaptionIsItalic": false,
                      "CaptionIsUnderline": false,
                      "CaptionBackColorT": "Transparent",
                      "CaptionForeColorT": "#222222",
                      "LabelStyle": "color: var(--mud-palette-text-primary) !important;background-color: Transparent;",
                      "ParentId": "Column10",
                      "Order": 0,
                      "CssCaptionFontSize": "16px",
                      "CssCaptionFontWeight": "normal",
                      "CssCaptionFontStyle": "normal",
                      "CssCaptionTextDecoration": "normal",
                      "CssCaptionColor": "var(--mud-palette-text-primary)",
                      "CssCaptionBackgroundColor": "white"
                    },
                    {
                      "$type": "Button",
                      "Style": 1,
                      "Size": 0,
                      "IsBlock": false,
                      "DefaultAction": 0,
                      "ServerId": "btnUpdate",
                      "Id": "btnUpdate",
                      "ControlType": 13,
                      "IsContainer": false,
                      "ControlTypeName": "Button",
                      "ParentColumnWidth": 12,
                      "Binding": {
                        "Id": "a7f31e11-9066-4506-b429-af0f008683f0",
                        "PhysicalFormId": "14a0ca1c-e783-4003-b109-aec200916cca",
                        "FormObjectField": "none",
                        "FormObjectFieldType": "none",
                        "CodeItemId": "bc6be719-d79c-4e94-8e50-af0f0098edf8",
                        "AutoPostBack": true,
                        "IsNotPostBack": false,
                        "FormControlId": "ab433c13-d827-4406-93ae-af0f0086359e"
                      },
                      "Behavior": {
                        "Id": "8ef095c2-c7b7-4799-b8e6-b2aa011c5673",
                        "FormBehaviorId": "bec41bef-6956-48bc-b59f-c99121003372",
                        "ControlState": 0,
                        "ControlStateEnum": 0,
                        "IMSState": "editable",
                        "Enabled": true,
                        "Visible": true,
                        "EnableNestedEdit": false,
                        "EnableNestedNew": false,
                        "EnableNestedDelete": false,
                        "EnableNestedView": false,
                        "EnableAttachmentUpload": true,
                        "EnableAttachmentDelete": true,
                        "EnableAttachmentDownload": true,
                        "EnableNestedSelect": false,
                        "EnableInlineNew": false,
                        "EnableInlineEdit": false,
                        "FormControlId": "ab433c13-d827-4406-93ae-af0f0086359e",
                        "EnableGanttNew": false,
                        "EnableGanttDelete": false,
                        "EnableAttachmentScan": true,
                        "EnableAttachmentEdit": false,
                        "EnableAttachmentRevert": false,
                        "EnableAttachmentNewVersion": false,
                        "RemoveType": 0,
                        "lastNonInvisibleState": 0
                      },
                      "Validators": [],
                      "IsMandatory": false,
                      "Caption": "Activate/Deactivate Users",
                      "CaptionPosition": 0,
                      "CaptionFontSize": 0,
                      "CaptionIsBold": false,
                      "CaptionIsItalic": false,
                      "CaptionIsUnderline": false,
                      "CaptionBackColorT": "Transparent",
                      "CaptionForeColorT": "#222222",
                      "LabelStyle": "color: var(--mud-palette-text-primary) !important;background-color: Transparent;",
                      "ParentId": "Column10",
                      "Order": 1,
                      "CssCaptionFontSize": "16px",
                      "CssCaptionFontWeight": "normal",
                      "CssCaptionFontStyle": "normal",
                      "CssCaptionTextDecoration": "normal",
                      "CssCaptionColor": "var(--mud-palette-text-primary)",
                      "CssCaptionBackgroundColor": "white"
                    }
                  ],
                  "ServerId": "Column10",
                  "Id": "Column10",
                  "ControlType": 1,
                  "IsContainer": true,
                  "ControlTypeName": "Column",
                  "ParentColumnWidth": 0,
                  "Behavior": {
                    "Id": "6dbf06b6-fd2b-4c05-a11b-b2aa011c567c",
                    "FormBehaviorId": "bec41bef-6956-48bc-b59f-c99121003372",
                    "ControlState": 0,
                    "ControlStateEnum": 0,
                    "IMSState": "editable",
                    "Enabled": true,
                    "Visible": true,
                    "EnableNestedEdit": false,
                    "EnableNestedNew": false,
                    "EnableNestedDelete": false,
                    "EnableNestedView": false,
                    "EnableAttachmentUpload": true,
                    "EnableAttachmentDelete": true,
                    "EnableAttachmentDownload": true,
                    "EnableNestedSelect": false,
                    "EnableInlineNew": false,
                    "EnableInlineEdit": false,
                    "FormControlId": "7539aaaa-dfb6-4f6a-a38c-af100081d116",
                    "EnableGanttNew": false,
                    "EnableGanttDelete": false,
                    "EnableAttachmentScan": true,
                    "EnableAttachmentEdit": false,
                    "EnableAttachmentRevert": false,
                    "EnableAttachmentNewVersion": false,
                    "RemoveType": 0,
                    "lastNonInvisibleState": 0
                  },
                  "Validators": [],
                  "IsMandatory": false,
                  "Caption": "Column",
                  "CaptionPosition": 0,
                  "CaptionFontSize": 0,
                  "CaptionIsBold": false,
                  "CaptionIsItalic": false,
                  "CaptionIsUnderline": false,
                  "CaptionBackColorT": "Transparent",
                  "CaptionForeColorT": "#222222",
                  "LabelStyle": "color: var(--mud-palette-text-primary) !important;background-color: Transparent;",
                  "ParentId": "Row8",
                  "Order": 0,
                  "CssCaptionFontSize": "16px",
                  "CssCaptionFontWeight": "normal",
                  "CssCaptionFontStyle": "normal",
                  "CssCaptionTextDecoration": "normal",
                  "CssCaptionColor": "var(--mud-palette-text-primary)",
                  "CssCaptionBackgroundColor": "white"
                }
              ],
              "Columns": [
                3,
                3,
                3,
                3
              ],
              "IsSection": false,
              "ServerId": "Row8",
              "Id": "Row8",
              "ControlType": 0,
              "IsContainer": true,
              "ControlTypeName": "Row",
              "ParentColumnWidth": 12,
              "Behavior": {
                "Id": "2d105b34-8b5c-4633-b662-b2aa011c567c",
                "FormBehaviorId": "bec41bef-6956-48bc-b59f-c99121003372",
                "ControlState": 0,
                "ControlStateEnum": 0,
                "IMSState": "editable",
                "Enabled": true,
                "Visible": true,
                "EnableNestedEdit": false,
                "EnableNestedNew": false,
                "EnableNestedDelete": false,
                "EnableNestedView": false,
                "EnableAttachmentUpload": true,
                "EnableAttachmentDelete": true,
                "EnableAttachmentDownload": true,
                "EnableNestedSelect": false,
                "EnableInlineNew": false,
                "EnableInlineEdit": false,
                "FormControlId": "c46861d1-1826-4c2e-b507-af100081cfd3",
                "EnableGanttNew": false,
                "EnableGanttDelete": false,
                "EnableAttachmentScan": true,
                "EnableAttachmentEdit": false,
                "EnableAttachmentRevert": false,
                "EnableAttachmentNewVersion": false,
                "RemoveType": 0,
                "lastNonInvisibleState": 0
              },
              "Validators": [],
              "IsMandatory": false,
              "CaptionPosition": 0,
              "CaptionFontSize": 0,
              "CaptionIsBold": false,
              "CaptionIsItalic": false,
              "CaptionIsUnderline": false,
              "CaptionBackColorT": "Transparent",
              "CaptionForeColorT": "#222222",
              "LabelStyle": "color: var(--mud-palette-text-primary) !important;background-color: Transparent;",
              "ParentId": "Column8",
              "Order": 0,
              "CssCaptionFontSize": "16px",
              "CssCaptionFontWeight": "normal",
              "CssCaptionFontStyle": "normal",
              "CssCaptionTextDecoration": "normal",
              "CssCaptionColor": "var(--mud-palette-text-primary)",
              "CssCaptionBackgroundColor": "white"
            },
            {
              "$type": "TextBox",
              "Mode": 2,
              "Height": 100,
              "Rows": 10,
              "Align": 3,
              "AlphaCharsOnly": false,
              "OnlyLatinChars": false,
              "MaxLength": 0,
              "BrowserAutoComplete": false,
              "ServerId": "Message",
              "Id": "Message",
              "ControlType": 3,
              "IsContainer": false,
              "ControlTypeName": "TextBox",
              "ParentColumnWidth": 12,
              "Binding": {
                "Id": "a0a41e45-e247-438f-98ae-aec3008c837b",
                "PhysicalFormId": "14a0ca1c-e783-4003-b109-aec200916cca",
                "FormObjectField": "ActionMessage",
                "FormObjectFieldType": "System.String",
                "AutoPostBack": false,
                "IsNotPostBack": false,
                "FormControlId": "a947db46-7656-4ef0-ba85-aec3008c1172"
              },
              "Behavior": {
                "Id": "3cf9c2c3-a2e7-4d94-9280-b2aa011c567c",
                "FormBehaviorId": "bec41bef-6956-48bc-b59f-c99121003372",
                "ControlState": 0,
                "ControlStateEnum": 0,
                "IMSState": "editable",
                "Enabled": true,
                "Visible": true,
                "EnableNestedEdit": false,
                "EnableNestedNew": false,
                "EnableNestedDelete": false,
                "EnableNestedView": false,
                "EnableAttachmentUpload": true,
                "EnableAttachmentDelete": true,
                "EnableAttachmentDownload": true,
                "EnableNestedSelect": false,
                "EnableInlineNew": false,
                "EnableInlineEdit": false,
                "FormControlId": "a947db46-7656-4ef0-ba85-aec3008c1172",
                "EnableGanttNew": false,
                "EnableGanttDelete": false,
                "EnableAttachmentScan": true,
                "EnableAttachmentEdit": false,
                "EnableAttachmentRevert": false,
                "EnableAttachmentNewVersion": false,
                "RemoveType": 0,
                "lastNonInvisibleState": 0
              },
              "Validators": [],
              "IsMandatory": false,
              "Caption": "Output Message",
              "CaptionPosition": 0,
              "CaptionFontSize": 16,
              "CaptionIsBold": true,
              "CaptionIsItalic": false,
              "CaptionIsUnderline": false,
              "CaptionBackColorT": "Transparent",
              "CaptionForeColorT": "#222222",
              "LabelStyle": "font-size: 16px;font-weight: bold;color: var(--mud-palette-text-primary) !important;background-color: Transparent;",
              "ParentId": "Column8",
              "Order": 2,
              "CssCaptionFontSize": "16px",
              "CssCaptionFontWeight": "normal",
              "CssCaptionFontStyle": "normal",
              "CssCaptionTextDecoration": "normal",
              "CssCaptionColor": "var(--mud-palette-text-primary)",
              "CssCaptionBackgroundColor": "white"
            }
          ],
          "ServerId": "Column8",
          "Id": "Column8",
          "ControlType": 1,
          "IsContainer": true,
          "ControlTypeName": "Column",
          "ParentColumnWidth": 0,
          "Behavior": {
            "Id": "e5602b9b-b6ad-4321-a942-b2aa011c567c",
            "FormBehaviorId": "bec41bef-6956-48bc-b59f-c99121003372",
            "ControlState": 0,
            "ControlStateEnum": 0,
            "IMSState": "editable",
            "Enabled": true,
            "Visible": true,
            "EnableNestedEdit": false,
            "EnableNestedNew": false,
            "EnableNestedDelete": false,
            "EnableNestedView": false,
            "EnableAttachmentUpload": true,
            "EnableAttachmentDelete": true,
            "EnableAttachmentDownload": true,
            "EnableNestedSelect": false,
            "EnableInlineNew": false,
            "EnableInlineEdit": false,
            "FormControlId": "4e6f67bc-de96-4c63-9149-aec200d14a5c",
            "EnableGanttNew": false,
            "EnableGanttDelete": false,
            "EnableAttachmentScan": true,
            "EnableAttachmentEdit": false,
            "EnableAttachmentRevert": false,
            "EnableAttachmentNewVersion": false,
            "RemoveType": 0,
            "lastNonInvisibleState": 0
          },
          "Validators": [],
          "IsMandatory": false,
          "Caption": "Column",
          "CaptionPosition": 0,
          "CaptionFontSize": 0,
          "CaptionIsBold": false,
          "CaptionIsItalic": false,
          "CaptionIsUnderline": false,
          "CaptionBackColorT": "Transparent",
          "CaptionForeColorT": "#222222",
          "LabelStyle": "color: var(--mud-palette-text-primary) !important;background-color: Transparent;",
          "ParentId": "Row6",
          "Order": 0,
          "CssCaptionFontSize": "16px",
          "CssCaptionFontWeight": "normal",
          "CssCaptionFontStyle": "normal",
          "CssCaptionTextDecoration": "normal",
          "CssCaptionColor": "var(--mud-palette-text-primary)",
          "CssCaptionBackgroundColor": "white"
        }
      ],
      "Columns": [
        12
      ],
      "IsSection": false,
      "ServerId": "Row6",
      "Id": "Row6",
      "ControlType": 0,
      "IsContainer": true,
      "ControlTypeName": "Row",
      "ParentColumnWidth": 0,
      "Behavior": {
        "Id": "5466b43b-b7fe-4bcf-9e02-b2aa011c5673",
        "FormBehaviorId": "bec41bef-6956-48bc-b59f-c99121003372",
        "ControlState": 0,
        "ControlStateEnum": 0,
        "IMSState": "editable",
        "Enabled": true,
        "Visible": true,
        "EnableNestedEdit": false,
        "EnableNestedNew": false,
        "EnableNestedDelete": false,
        "EnableNestedView": false,
        "EnableAttachmentUpload": true,
        "EnableAttachmentDelete": true,
        "EnableAttachmentDownload": true,
        "EnableNestedSelect": false,
        "EnableInlineNew": false,
        "EnableInlineEdit": false,
        "FormControlId": "1e6d651b-4a58-4209-8d32-aec200d149e1",
        "EnableGanttNew": false,
        "EnableGanttDelete": false,
        "EnableAttachmentScan": true,
        "EnableAttachmentEdit": false,
        "EnableAttachmentRevert": false,
        "EnableAttachmentNewVersion": false,
        "RemoveType": 0,
        "lastNonInvisibleState": 0
      },
      "Validators": [],
      "IsMandatory": false,
      "CaptionPosition": 0,
      "CaptionFontSize": 0,
      "CaptionIsBold": false,
      "CaptionIsItalic": false,
      "CaptionIsUnderline": false,
      "CaptionBackColorT": "Transparent",
      "CaptionForeColorT": "#222222",
      "LabelStyle": "color: var(--mud-palette-text-primary) !important;background-color: Transparent;",
      "Order": 8,
      "CssCaptionFontSize": "16px",
      "CssCaptionFontWeight": "normal",
      "CssCaptionFontStyle": "normal",
      "CssCaptionTextDecoration": "normal",
      "CssCaptionColor": "var(--mud-palette-text-primary)",
      "CssCaptionBackgroundColor": "white"
    },
    {
      "IsBorder": false,
      "BorderColor": "Black",
      "ColorRgba": "#000000",
      "ColumnsList": [
        {
          "Width": 12,
          "IsBorder": false,
          "IsDefaultColor": false,
          "BackColorEnable": true,
          "BorderColor": "Black",
          "ColorRgba": "#000000",
          "BackgroundColor": "Transparent",
          "BackgroundColorRgba": "#ffffff",
          "Controls": [
            {
              "$type": "Row",
              "IsBorder": false,
              "BorderColor": "Black",
              "ColorRgba": "#000000",
              "ColumnsList": [
                {
                  "Width": 12,
                  "IsBorder": false,
                  "IsDefaultColor": false,
                  "BackColorEnable": true,
                  "BorderColor": "Black",
                  "ColorRgba": "#000000",
                  "BackgroundColor": "Transparent",
                  "BackgroundColorRgba": "#ffffff",
                  "Controls": [],
                  "ServerId": "Column1",
                  "Id": "Column1",
                  "ControlType": 1,
                  "IsContainer": true,
                  "ControlTypeName": "Column",
                  "ParentColumnWidth": 0,
                  "Behavior": {
                    "Id": "1002fa32-3f68-4421-8a01-b2aa011c567c",
                    "FormBehaviorId": "bec41bef-6956-48bc-b59f-c99121003372",
                    "ControlState": 0,
                    "ControlStateEnum": 0,
                    "IMSState": "editable",
                    "Enabled": true,
                    "Visible": true,
                    "EnableNestedEdit": false,
                    "EnableNestedNew": false,
                    "EnableNestedDelete": false,
                    "EnableNestedView": false,
                    "EnableAttachmentUpload": true,
                    "EnableAttachmentDelete": true,
                    "EnableAttachmentDownload": true,
                    "EnableNestedSelect": false,
                    "EnableInlineNew": false,
                    "EnableInlineEdit": false,
                    "FormControlId": "95d67392-2aba-48bb-b914-aec2009525fd",
                    "EnableGanttNew": false,
                    "EnableGanttDelete": false,
                    "EnableAttachmentScan": true,
                    "EnableAttachmentEdit": false,
                    "EnableAttachmentRevert": false,
                    "EnableAttachmentNewVersion": false,
                    "RemoveType": 0,
                    "lastNonInvisibleState": 0
                  },
                  "Validators": [],
                  "IsMandatory": false,
                  "Caption": "Column",
                  "CaptionPosition": 0,
                  "CaptionFontSize": 0,
                  "CaptionIsBold": false,
                  "CaptionIsItalic": false,
                  "CaptionIsUnderline": false,
                  "CaptionBackColorT": "Transparent",
                  "CaptionForeColorT": "#222222",
                  "LabelStyle": "color: var(--mud-palette-text-primary) !important;background-color: Transparent;",
                  "ParentId": "Row1",
                  "Order": 0,
                  "CssCaptionFontSize": "16px",
                  "CssCaptionFontWeight": "normal",
                  "CssCaptionFontStyle": "normal",
                  "CssCaptionTextDecoration": "normal",
                  "CssCaptionColor": "var(--mud-palette-text-primary)",
                  "CssCaptionBackgroundColor": "white"
                }
              ],
              "Columns": [
                12
              ],
              "IsSection": false,
              "ServerId": "Row1",
              "Id": "Row1",
              "ControlType": 0,
              "IsContainer": true,
              "ControlTypeName": "Row",
              "ParentColumnWidth": 12,
              "Behavior": {
                "Id": "df9dfdd4-edc1-492f-9562-b2aa011c5673",
                "FormBehaviorId": "bec41bef-6956-48bc-b59f-c99121003372",
                "ControlState": 0,
                "ControlStateEnum": 0,
                "IMSState": "editable",
                "Enabled": true,
                "Visible": true,
                "EnableNestedEdit": false,
                "EnableNestedNew": false,
                "EnableNestedDelete": false,
                "EnableNestedView": false,
                "EnableAttachmentUpload": true,
                "EnableAttachmentDelete": true,
                "EnableAttachmentDownload": true,
                "EnableNestedSelect": false,
                "EnableInlineNew": false,
                "EnableInlineEdit": false,
                "FormControlId": "cec584d2-d188-4bbc-8541-aec2009525fd",
                "EnableGanttNew": false,
                "EnableGanttDelete": false,
                "EnableAttachmentScan": true,
                "EnableAttachmentEdit": false,
                "EnableAttachmentRevert": false,
                "EnableAttachmentNewVersion": false,
                "RemoveType": 0,
                "lastNonInvisibleState": 0
              },
              "Validators": [],
              "IsMandatory": false,
              "CaptionPosition": 0,
              "CaptionFontSize": 0,
              "CaptionIsBold": false,
              "CaptionIsItalic": false,
              "CaptionIsUnderline": false,
              "CaptionBackColorT": "Transparent",
              "CaptionForeColorT": "#222222",
              "LabelStyle": "color: var(--mud-palette-text-primary) !important;background-color: Transparent;",
              "ParentId": "Column",
              "Order": 10,
              "CssCaptionFontSize": "16px",
              "CssCaptionFontWeight": "normal",
              "CssCaptionFontStyle": "normal",
              "CssCaptionTextDecoration": "normal",
              "CssCaptionColor": "var(--mud-palette-text-primary)",
              "CssCaptionBackgroundColor": "white"
            }
          ],
          "ServerId": "Column",
          "Id": "Column",
          "ControlType": 1,
          "IsContainer": true,
          "ControlTypeName": "Column",
          "ParentColumnWidth": 0,
          "Behavior": {
            "Id": "5867cec8-b81d-4b73-bc98-b2aa011c567c",
            "FormBehaviorId": "bec41bef-6956-48bc-b59f-c99121003372",
            "ControlState": 0,
            "ControlStateEnum": 0,
            "IMSState": "editable",
            "Enabled": true,
            "Visible": true,
            "EnableNestedEdit": false,
            "EnableNestedNew": false,
            "EnableNestedDelete": false,
            "EnableNestedView": false,
            "EnableAttachmentUpload": true,
            "EnableAttachmentDelete": true,
            "EnableAttachmentDownload": true,
            "EnableNestedSelect": false,
            "EnableInlineNew": false,
            "EnableInlineEdit": false,
            "FormControlId": "62e4df9c-1ce6-4480-ac4b-aec2009525fc",
            "EnableGanttNew": false,
            "EnableGanttDelete": false,
            "EnableAttachmentScan": true,
            "EnableAttachmentEdit": false,
            "EnableAttachmentRevert": false,
            "EnableAttachmentNewVersion": false,
            "RemoveType": 0,
            "lastNonInvisibleState": 0
          },
          "Validators": [],
          "IsMandatory": false,
          "Caption": "Column",
          "CaptionPosition": 0,
          "CaptionFontSize": 0,
          "CaptionIsBold": false,
          "CaptionIsItalic": false,
          "CaptionIsUnderline": false,
          "CaptionBackColorT": "Transparent",
          "CaptionForeColorT": "#222222",
          "LabelStyle": "color: var(--mud-palette-text-primary) !important;background-color: Transparent;",
          "ParentId": "Row",
          "Order": 0,
          "CssCaptionFontSize": "16px",
          "CssCaptionFontWeight": "normal",
          "CssCaptionFontStyle": "normal",
          "CssCaptionTextDecoration": "normal",
          "CssCaptionColor": "var(--mud-palette-text-primary)",
          "CssCaptionBackgroundColor": "white"
        }
      ],
      "Columns": [
        12
      ],
      "IsSection": false,
      "ServerId": "Row",
      "Id": "Row",
      "ControlType": 0,
      "IsContainer": true,
      "ControlTypeName": "Row",
      "ParentColumnWidth": 0,
      "Behavior": {
        "Id": "4cfdb59c-be46-4adb-8061-b2aa011c5673",
        "FormBehaviorId": "bec41bef-6956-48bc-b59f-c99121003372",
        "ControlState": 0,
        "ControlStateEnum": 0,
        "IMSState": "editable",
        "Enabled": true,
        "Visible": true,
        "EnableNestedEdit": false,
        "EnableNestedNew": false,
        "EnableNestedDelete": false,
        "EnableNestedView": false,
        "EnableAttachmentUpload": true,
        "EnableAttachmentDelete": true,
        "EnableAttachmentDownload": true,
        "EnableNestedSelect": false,
        "EnableInlineNew": false,
        "EnableInlineEdit": false,
        "FormControlId": "2a17241d-0fec-4128-802d-aec2009525fb",
        "EnableGanttNew": false,
        "EnableGanttDelete": false,
        "EnableAttachmentScan": true,
        "EnableAttachmentEdit": false,
        "EnableAttachmentRevert": false,
        "EnableAttachmentNewVersion": false,
        "RemoveType": 0,
        "lastNonInvisibleState": 0
      },
      "Validators": [],
      "IsMandatory": false,
      "CaptionPosition": 0,
      "CaptionFontSize": 0,
      "CaptionIsBold": false,
      "CaptionIsItalic": false,
      "CaptionIsUnderline": false,
      "CaptionBackColorT": "Transparent",
      "CaptionForeColorT": "#222222",
      "LabelStyle": "color: var(--mud-palette-text-primary) !important;background-color: Transparent;",
      "Order": 9,
      "CssCaptionFontSize": "16px",
      "CssCaptionFontWeight": "normal",
      "CssCaptionFontStyle": "normal",
      "CssCaptionTextDecoration": "normal",
      "CssCaptionColor": "var(--mud-palette-text-primary)",
      "CssCaptionBackgroundColor": "white"
    }
  ],
  "FormObject": {
    "btnImport": null,
    "btnUpdate": null,
    "DownloadExcelTemplate": null,
    "Label": null,
    "Label2": null,
    "Label3": null,
    "Label5": null,
    "Message": null,
    "RadioButtonList": "0",
    "UploadFilewithData": null,
    "ValidateMessage": null
  },
  "ChangedValues": {},
  "CaptionPosition": 0,
  "ControlValidations": {},
  "ControlsField": {
    "btnImport": "btnImport",
    "btnUpdate": "btnUpdate",
    "DownloadExcelTemplate": "ImportFileTemplate",
    "Message": "ActionMessage",
    "RadioButtonList": "ExportType",
    "UploadFilewithData": "ImportFile",
    "ValidateMessage": "ValidationMessage"
  },
  "AllRules": {},
  "AppliedRules": {},
  "IsSubmitButton": false,
  "IsCanSave": false,
  "IsServerError": false,
  "IsCanExport": false,
  "FilesData": [],
  "NestedForms": {},
  "FilterClause": {}
}